sgl_jax/__init__.py
sgl_jax/__main__.py
sgl_jax/bench_offline_throughput.py
sgl_jax/bench_one_batch.py
sgl_jax/bench_one_batch_server.py
sgl_jax/bench_serving.py
sgl_jax/check_env.py
sgl_jax/global_config.py
sgl_jax/launch_server.py
sgl_jax/profiler.py
sgl_jax/utils.py
sgl_jax/version.py
sgl_jax/srt/__init__.py
sgl_jax/srt/conversation.py
sgl_jax/srt/hf_transformers_utils.py
sgl_jax/srt/jinja_template_utils.py
sgl_jax/srt/memory_profiler.py
sgl_jax/srt/precision_tracer.py
sgl_jax/srt/reasoning_parser.py
sgl_jax/srt/server_args.py
sgl_jax/srt/configs/__init__.py
sgl_jax/srt/configs/load_config.py
sgl_jax/srt/configs/model_config.py
sgl_jax/srt/entrypoints/EngineBase.py
sgl_jax/srt/entrypoints/engine.py
sgl_jax/srt/entrypoints/http_server.py
sgl_jax/srt/entrypoints/openai/__init__.py
sgl_jax/srt/entrypoints/openai/protocol.py
sgl_jax/srt/entrypoints/openai/serving_base.py
sgl_jax/srt/entrypoints/openai/serving_chat.py
sgl_jax/srt/entrypoints/openai/serving_completions.py
sgl_jax/srt/entrypoints/openai/serving_embedding.py
sgl_jax/srt/entrypoints/openai/serving_rerank.py
sgl_jax/srt/entrypoints/openai/serving_score.py
sgl_jax/srt/entrypoints/openai/usage_processor.py
sgl_jax/srt/entrypoints/openai/utils.py
sgl_jax/srt/function_call/base_format_detector.py
sgl_jax/srt/function_call/core_types.py
sgl_jax/srt/function_call/ebnf_composer.py
sgl_jax/srt/function_call/function_call_parser.py
sgl_jax/srt/function_call/qwen3_coder_detector.py
sgl_jax/srt/function_call/utils.py
sgl_jax/srt/layers/binary_search.py
sgl_jax/srt/layers/embeddings.py
sgl_jax/srt/layers/layernorm.py
sgl_jax/srt/layers/linear.py
sgl_jax/srt/layers/logits_processor.py
sgl_jax/srt/layers/moe.py
sgl_jax/srt/layers/radix_attention.py
sgl_jax/srt/layers/sampler.py
sgl_jax/srt/layers/attention/base_attn_backend.py
sgl_jax/srt/layers/attention/flashattention_backend.py
sgl_jax/srt/layers/attention/native_backend.py
sgl_jax/srt/layers/attention/flash_attn_kernel/flash_attention.py
sglang_jax-0.0.2.dist-info/licenses/LICENSE
sglang_jax-0.0.2.dist-info/METADATA
sglang_jax-0.0.2.dist-info/WHEEL
sglang_jax-0.0.2.dist-info/top_level.txt
sglang_jax-0.0.2.dist-info/RECORD
