Metadata-Version: 2.4
Name: sglang-jax
Version: 0.0.2
Summary: JAX backend for SGL
License:                                  Apache License
Requires-Python: >=3.12
License-File: LICENSE
Requires-Dist: fastapi~=0.116.1
Requires-Dist: flax~=0.12.0
Requires-Dist: huggingface-hub~=0.34.3
Requires-Dist: jax[tpu]~=0.8.0
Requires-Dist: jinja2~=3.1.6
Requires-Dist: modelscope~=1.28.2
Requires-Dist: msgpack-python~=0.5.6
Requires-Dist: numpy~=2.2.6
Requires-Dist: orjson~=3.11.1
Requires-Dist: pillow~=11.3.0
Requires-Dist: psutil~=7.0.0
Requires-Dist: pydantic~=2.11.7
Requires-Dist: python-multipart>=0.0.20
Requires-Dist: pyzmq~=27.0.1
Requires-Dist: requests~=2.32.4
Requires-Dist: safetensors~=0.6.1
Requires-Dist: setproctitle~=1.3.6
Requires-Dist: tiktoken>=0.10.0
Requires-Dist: transformers~=4.55.0
Requires-Dist: typing-extensions~=4.14.1
Requires-Dist: uvicorn~=0.35.0
Requires-Dist: uvloop~=0.21.0
Requires-Dist: psutil
Requires-Dist: httpx
Requires-Dist: openai
Requires-Dist: pandas
Requires-Dist: aiohttp
Requires-Dist: pybase64
Requires-Dist: partial_json_parser
Provides-Extra: dev
Dynamic: license-file
